siemens_standard_bom/__init__.py
siemens_standard_bom/immutable.py
siemens_standard_bom/model.py
siemens_standard_bom/parser.py
siemens_standard_bom/py.typed
siemens_standard_bom-4.0.0.dist-info/LICENSE
siemens_standard_bom-4.0.0.dist-info/METADATA
siemens_standard_bom-4.0.0.dist-info/WHEEL
siemens_standard_bom-4.0.0.dist-info/RECORD
