Metadata-Version: 2.3
Name: siemens-standard-bom
Version: 4.0.0
Summary: Standard BOM Format Library
License: MIT
Keywords: sbom,software-bill-of-materials,cyclonedx,cdx
Author: Hakan Dilek
Author-email: hakan.dilek@siemens.com
Requires-Python: >=3.10,<4.0
Classifier: Development Status :: 5 - Production/Stable
Classifier: Intended Audience :: Developers
Classifier: Natural Language :: English
Classifier: Operating System :: OS Independent
Classifier: Topic :: Software Development
Classifier: Programming Language :: Python :: 3
Classifier: Programming Language :: Python :: 3.10
Classifier: Programming Language :: Python :: 3.11
Classifier: Programming Language :: Python :: 3.12
Classifier: Programming Language :: Python :: 3.13
Requires-Dist: cyclonedx-python-lib (>=9.1.0,<10.0.0)
Requires-Dist: python-dateutil (>=2.9.0.post0,<3.0.0)
Project-URL: Bug Tracker, https://github.com/siemens/standard-bom-python/issues
Project-URL: Documentation, https://github.com/siemens/standard-bom-python/blob/main/README.md
Project-URL: Homepage, https://sbom.siemens.io/
Project-URL: Repository, https://github.com/siemens/standard-bom-python
